Metadata-Version: 2.1
Name: ez-localizr
Version: 0.0.3
Summary: An insanely simple localization tool for Python.
Author: Tyler Koziol
Author-email: tora@tora-ouji.com
Classifier: Programming Language :: Python :: 3
Classifier: License :: OSI Approved :: MIT License
Classifier: Operating System :: OS Independent
Requires-Python: >=3.8
Requires-Dist: PyYAML
Requires-Dist: ftfy
